qtmimport/__init__.py
qtmimport/qtmimport.py
qtmimport-1.1.0.dist-info/METADATA
qtmimport-1.1.0.dist-info/WHEEL
qtmimport-1.1.0.dist-info/licenses/LICENSE
qtmimport-1.1.0.dist-info/RECORD
